icad_tone_detection/__init__.py
icad_tone_detection/audio_loader.py
icad_tone_detection/cli.py
icad_tone_detection/exceptions.py
icad_tone_detection/frequency_extraction.py
icad_tone_detection/main.py
icad_tone_detection/tone_detection.py
icad_tone_detection/bin/linux_arm64/icad_decode
icad_tone_detection/bin/linux_armv7/icad_decode
icad_tone_detection/bin/linux_x86_64/icad_decode
icad_tone_detection/bin/macos_arm64/icad_decode
icad_tone_detection/bin/macos_x84_64/icad_decode
icad_tone_detection/bin/windows_x86_64/icad_decode.exe
icad_tone_detection/examples/__init__.py
icad_tone_detection/examples/detect_test.py
icad_tone_detection/examples/example_audio/dtmf_example.wav
icad_tone_detection/examples/example_audio/hi_low_tone_example.wav
icad_tone_detection/examples/example_audio/long_tone_example.wav
icad_tone_detection/examples/example_audio/mdc_example.wav
icad_tone_detection/examples/example_audio/pulsed_example.wav
icad_tone_detection/examples/example_audio/two_tone_example.wav
icad_tone_detection-2.9.0.dist-info/licenses/LICENSE
icad_tone_detection-2.9.0.dist-info/METADATA
icad_tone_detection-2.9.0.dist-info/WHEEL
icad_tone_detection-2.9.0.dist-info/entry_points.txt
icad_tone_detection-2.9.0.dist-info/top_level.txt
icad_tone_detection-2.9.0.dist-info/RECORD
