Metadata-Version: 2.4
Name: icad_tone_detection
Version: 2.9.0
Summary: A Python library for extracting scanner radio tones from scanner audio.
Author-email: TheGreatCodeholio <ian@icarey.net>
Project-URL: Homepage, https://github.com/thegreatcodeholio/icad_tone_detection
Project-URL: Issues, https://github.com/thegreatcodeholio/icad_tone_detection/issues
Classifier: Programming Language :: Python :: 3
Classifier: License :: OSI Approved :: MIT License
Classifier: Operating System :: OS Independent
Requires-Python: >=3.9
License-File: LICENSE
Requires-Dist: numpy>=1.26.4
Requires-Dist: requests>=2.31.0
Requires-Dist: pydub>=0.25.1
Requires-Dist: scipy>=1.12.0
Dynamic: license-file
